vrscene_parser/__init__.py
vrscene_parser/main.py
vrscene_parser/prompts.py
vrscene_parser-2025.12.21134443.dist-info/METADATA
vrscene_parser-2025.12.21134443.dist-info/WHEEL
vrscene_parser-2025.12.21134443.dist-info/top_level.txt
vrscene_parser-2025.12.21134443.dist-info/RECORD
