Metadata-Version: 2.4
Name: vrscene-parser
Version: 2025.12.21134443
Summary: A new package would process textual descriptions of virtual reality scenes or environments and return structured, validated outputs that describe the scene in a standardized format. It would use an LL
Author-email: vrscene-parser <hi@eugene.plus>
License: MIT
Project-URL: Homepage, https://github.com/chigwell/vrscene-parser
Requires-Python: >=3.9
Requires-Dist: langchain-llm7>=0.0.0
Requires-Dist: llmatch-messages>=0.0.0
Requires-Dist: langchain-core>=0.3.0
